ventoyl/__init__.py
ventoyl/ventoyl.py
ventoyl/etc/url_config.json
ventoyu-0.3.data/scripts/ventoyu
ventoyu-0.3.dist-info/LICENSE
ventoyu-0.3.dist-info/METADATA
ventoyu-0.3.dist-info/WHEEL
ventoyu-0.3.dist-info/top_level.txt
ventoyu-0.3.dist-info/RECORD
