Metadata-Version: 2.1
Name: ventoyu
Version: 0.3
Summary: Manage and update ISO files on Ventoy devices
Home-page: https://github.com/mawigh/ventoy_updater
Author: Marcel-Brian Wilkowsky
Author-email: marcel.wilkowsky@hotmail.de
License: UNKNOWN
Project-URL: Bug Tracker, https://github.com/mawigh/ventoy_updater/issues
Platform: UNKNOWN
Classifier: Programming Language :: Python :: 3
Classifier: License :: OSI Approved :: GNU General Public License v3 (GPLv3)
Classifier: Operating System :: Unix
License-File: LICENSE
Requires-Dist: beautifulsoup4
Requires-Dist: requests
